inmanta_plugins/cron/__init__.py
inmanta_plugins/cron/setup.cfg
inmanta_plugins/cron/model/_init.cf
inmanta_plugins/cron/templates/cronjob.j2
inmanta_module_cron-1.0.13.dist-info/METADATA
inmanta_module_cron-1.0.13.dist-info/WHEEL
inmanta_module_cron-1.0.13.dist-info/top_level.txt
inmanta_module_cron-1.0.13.dist-info/RECORD
