Metadata-Version: 2.1
Name: inmanta-module-cron
Version: 1.0.13
License: Apache 2.0
Requires-Dist: inmanta-module-std
